modterm/__init__.py
modterm/__main__.py
modterm/components/__init__.py
modterm/components/analyse_window.py
modterm/components/config_handler.py
modterm/components/definitions.py
modterm/components/export_menu.py
modterm/components/header_menu.py
modterm/components/help.py
modterm/components/hepers.py
modterm/components/ip_sweep_menu.py
modterm/components/menu_base.py
modterm/components/modbus_handler.py
modterm/components/popup_message.py
modterm/components/read_registers_menu.py
modterm/components/scrollable_list.py
modterm/components/serial_interface_scan.py
modterm/components/unit_sweep_menu.py
modterm/components/window_base.py
modterm/components/write_registers_menu.py
modterm-1.3.1.dist-info/licenses/LICENSE.txt
modterm-1.3.1.dist-info/METADATA
modterm-1.3.1.dist-info/WHEEL
modterm-1.3.1.dist-info/entry_points.txt
modterm-1.3.1.dist-info/top_level.txt
modterm-1.3.1.dist-info/RECORD
