Metadata-Version: 2.4
Name: ModTerm
Version: 1.3.1
Summary: A modbus analyser written in pure Python
Author-email: Máté Szabó <mate@mateszabo.com>
Project-URL: Homepage, https://github.com/matesh/modterm
Project-URL: Issues, https://github.com/matesh/modterm/issues
Classifier: Programming Language :: Python :: 3
Classifier: License :: OSI Approved :: GNU General Public License v3 (GPLv3)
Classifier: Operating System :: OS Independent
Requires-Python: >=3.9
License-File: LICENSE.txt
Requires-Dist: pymodbus<=3.6.9
Requires-Dist: pyserial
Dynamic: license-file
